fridgeos/__init__.py
fridgeos/hal/__init__.py
fridgeos/hal/client.py
fridgeos/hal/server.py
fridgeos/hal/drivers/dummy.py
fridgeos/hal/drivers/haldrivers.py
fridgeos/hal/drivers/korad_kd3005p.py
fridgeos/hal/drivers/srs_sim921.py
fridgeos/hal/drivers/srs_sim922.py
fridgeos/hal/drivers/swarm.py
fridgeos/monitor/__init__.py
fridgeos/monitor/client.py
fridgeos/monitor/server.py
fridgeos/scraper/__init__.py
fridgeos/scraper/scraper.py
fridgeos/statemachine/__init__.py
fridgeos/statemachine/continous_dr.py
fridgeos/statemachine/single_shot_1k.py
fridgeos/statemachine/state_machine_1k.py
fridgeos/statemachine/utilities/zmqhelpers/example1.py
fridgeos/statemachine/utilities/zmqhelpers/example2.py
fridgeos/statemachine/utilities/zmqhelpers/example3.py
fridgeos/statemachine/utilities/zmqhelpers/setup.py
fridgeos/statemachine/utilities/zmqhelpers/zmqhelper/__init__.py
fridgeos/statemachine/utilities/zmqhelpers/zmqhelper/client.py
fridgeos/statemachine/utilities/zmqhelpers/zmqhelper/fridgeOS_client.py
fridgeos/statemachine/utilities/zmqhelpers/zmqhelper/server.py
fridgeos/statemachine/utilities/zmqhelpers/zmqhelper/untitled0.py
fridgeos/zmqhelper/__init__.py
fridgeos/zmqhelper/client.py
fridgeos/zmqhelper/server.py
fridgeos-0.2.0.dist-info/licenses/LICENSE
fridgeos-0.2.0.dist-info/METADATA
fridgeos-0.2.0.dist-info/WHEEL
fridgeos-0.2.0.dist-info/top_level.txt
fridgeos-0.2.0.dist-info/RECORD
