Metadata-Version: 2.4
Name: fridgeos
Version: 0.2.0
Summary: Simple, easy-to-use control software for cryostats
Author-email: Adam McCaughan <adam.mccaughan@nist.gov>, Ryan Morgenstern <ryan.morgenstern@nist.gov>
License: CC BY-SA
Project-URL: Homepage, https://github.com/amccaugh/fridgeos
License-File: LICENSE
Requires-Dist: psycopg2-binary
Requires-Dist: pandas
Requires-Dist: requests
Requires-Dist: pyserial
Requires-Dist: pyzmq
Requires-Dist: python-statemachine
Requires-Dist: simple_pid
Dynamic: license-file
